OMC_scan_funs_no_pandas_v2.py
peak_finder.py
real_time_scan.py
setup.py
OMC_scan_funs.egg-info/PKG-INFO
OMC_scan_funs.egg-info/SOURCES.txt
OMC_scan_funs.egg-info/dependency_links.txt
OMC_scan_funs.egg-info/top_level.txt