Metadata-Version: 1.0
Name: OMC-scan-funs
Version: 0.1
Summary: A library of functions for parsing LIGO OMC scans
Home-page: UNKNOWN
Author: Alexei Ciobanu
Author-email: alexei.ciobanu95@gmail.com
License: UNKNOWN
Platform: UNKNOWN
